{
    "success": false,
    "note": 20,
    "jeux_de_donnees": [
        {
            "name": "ordre_attaque",
            "data": [
                "a",
                "b",
                "w",
                "d",
                "u",
                "v",
                "w",
                "e",
                "f",
                "g",
                "h",
                "i",
                "j",
                "k",
                "l",
                "m",
                "n",
                "o",
                "p",
                "q",
                "r",
                "s",
                "t",
                "u",
                "v",
                "w",
                "w",
                "x",
                "y",
                "z",
                "w",
                "w",
                "x",
                "y",
                "n",
                "o",
                "p"
            ],
            "hidden": false,
            "validation": true,
            "resultat_utilisateur": [
                "a",
                "b",
                "w",
                "d",
                "u",
                "v",
                "w",
                "e",
                "f",
                "g",
                "h",
                "i",
                "j",
                "k",
                "l",
                "m",
                "n",
                "o",
                "p",
                "q",
                "r",
                "s",
                "t",
                "u",
                "v",
                "w",
                "w",
                "x",
                "y",
                "z",
                "w",
                "w",
                "x",
                "y",
                "n",
                "o",
                "p"
            ],
            "correction": [
                "a",
                "b",
                "w",
                "d",
                "u",
                "v",
                "w",
                "e",
                "f",
                "g",
                "h",
                "i",
                "j",
                "k",
                "l",
                "m",
                "n",
                "o",
                "p",
                "q",
                "r",
                "s",
                "t",
                "u",
                "v",
                "w",
                "w",
                "x",
                "y",
                "z",
                "w",
                "w",
                "x",
                "y",
                "n",
                "o",
                "p"
            ],
            "impact": 14
        },
        {
            "name": "Jeu de donn\u00e9es cach\u00e9 1",
            "data": [
                "a",
                "b",
                "w",
                "d",
                "u",
                "v",
                "w",
                "e",
                "f",
                "g",
                "h",
                "i",
                "j",
                "k",
                "l",
                "m",
                "n",
                "o",
                "p",
                "q",
                "r",
                "s",
                "t",
                "u",
                "v",
                "w",
                "w",
                "x",
                "y",
                "z",
                "w",
                "w",
                "x",
                "y",
                "n",
                "o",
                "p"
            ],
            "hidden": true,
            "validation": true,
            "resultat_utilisateur": [
                "a",
                "b",
                "w",
                "d",
                "u",
                "v",
                "w",
                "e",
                "f",
                "g",
                "h",
                "i",
                "j",
                "k",
                "l",
                "m",
                "n",
                "o",
                "p",
                "q",
                "r",
                "s",
                "t",
                "u",
                "v",
                "w",
                "w",
                "x",
                "y",
                "z",
                "w",
                "w",
                "x",
                "y",
                "n",
                "o",
                "p"
            ],
            "correction": [
                "a",
                "b",
                "w",
                "d",
                "u",
                "v",
                "w",
                "e",
                "f",
                "g",
                "h",
                "i",
                "j",
                "k",
                "l",
                "m",
                "n",
                "o",
                "p",
                "q",
                "r",
                "s",
                "t",
                "u",
                "v",
                "w",
                "w",
                "x",
                "y",
                "z",
                "w",
                "w",
                "x",
                "y",
                "n",
                "o",
                "p"
            ],
            "impact": 3
        },
        {
            "name": "Jeu de donn\u00e9es cach\u00e9 2",
            "data": [
                "a",
                "b",
                "w",
                "d",
                "u",
                "v",
                "w",
                "e",
                "f",
                "g",
                "h",
                "i",
                "j",
                "k",
                "l",
                "m",
                "n",
                "o",
                "p",
                "q",
                "r",
                "s",
                "t",
                "u",
                "v",
                "w",
                "w",
                "x",
                "y",
                "z",
                "w",
                "w",
                "x",
                "y",
                "n",
                "o",
                "p"
            ],
            "hidden": true,
            "validation": true,
            "resultat_utilisateur": [
                "a",
                "b",
                "w",
                "d",
                "u",
                "v",
                "w",
                "e",
                "f",
                "g",
                "h",
                "i",
                "j",
                "k",
                "l",
                "m",
                "n",
                "o",
                "p",
                "q",
                "r",
                "s",
                "t",
                "u",
                "v",
                "w",
                "w",
                "x",
                "y",
                "z",
                "w",
                "w",
                "x",
                "y",
                "n",
                "o",
                "p"
            ],
            "correction": [
                "a",
                "b",
                "w",
                "d",
                "u",
                "v",
                "w",
                "e",
                "f",
                "g",
                "h",
                "i",
                "j",
                "k",
                "l",
                "m",
                "n",
                "o",
                "p",
                "q",
                "r",
                "s",
                "t",
                "u",
                "v",
                "w",
                "w",
                "x",
                "y",
                "z",
                "w",
                "w",
                "x",
                "y",
                "n",
                "o",
                "p"
            ],
            "impact": 3
        }
    ],
    "contraintes": [
        {
            "name": "Pas de append",
            "validation": true,
            "message": "Vous avez utilis\u00e9 la fonction append. L'exercice n'est pas valid\u00e9",
            "impact": 20
        },
        {
            "name": "Pas de remove",
            "validation": true,
            "message": "Vous avez utilis\u00e9 la fonction remove. L'exercice n'est pas valid\u00e9",
            "impact": 15
        }
    ],
    "bonus": [],
    "console": {
        "type": null,
        "message": []
    }
}